fifpy/FIFpy.py
fifpy/IF_aux.py
fifpy/IFpy.py
fifpy/IMFogram_v1.py
fifpy/MIF3D.py
fifpy/MIFpy.py
fifpy/MvFIFpy.py
fifpy/MvIFpy.py
fifpy/__init__.py
fifpy/arrays.py
fifpy/fif_tools.py
fifpy/prefixed_double_filter.py
fifpy/time_1.py
iterativefiltering-1.0.2.dist-info/LICENSE
iterativefiltering-1.0.2.dist-info/METADATA
iterativefiltering-1.0.2.dist-info/WHEEL
iterativefiltering-1.0.2.dist-info/top_level.txt
iterativefiltering-1.0.2.dist-info/RECORD
