Metadata-Version: 2.1
Name: iterativefiltering
Version: 1.0.2
Summary: Python Package for Iterative Filtering decomposition methods
Author-email: Emanuele Papini <emanuele.papini@inaf.it>
Maintainer-email: Emanuele Papini <emanuele.papini@inaf.it>
License: MIT License
Project-URL: Homepage, https://github.com/EmanuelePapini/fifpy
Keywords: data analysis,time series,adaptive decomposition
Classifier: Development Status :: 5 - Production/Stable
Classifier: License :: OSI Approved :: MIT License
Classifier: Programming Language :: Python :: 3
Classifier: Topic :: Scientific/Engineering
Classifier: Intended Audience :: Science/Research
Requires-Python: <3.13
License-File: LICENSE
Requires-Dist: numba
Requires-Dist: attrdict
Requires-Dist: matplotlib
Requires-Dist: numpy
Requires-Dist: scipy
Requires-Dist: scikit-learn
